[
    {
        "name": "신재희",
        "date": "2026. 3. 31. 오후 06:17",
        "score": 9,
        "total": 10,
        "items": [
            {
                "q": 1,
                "correct": true
            },
            {
                "q": 2,
                "correct": true
            },
            {
                "q": 3,
                "correct": true
            },
            {
                "q": 4,
                "correct": true
            },
            {
                "q": 5,
                "correct": true
            },
            {
                "q": 6,
                "correct": false
            },
            {
                "q": 7,
                "correct": true
            },
            {
                "q": 8,
                "correct": true
            },
            {
                "q": 9,
                "correct": true
            },
            {
                "q": 10,
                "correct": true
            }
        ]
    }
]